not-hotdog/__init__.py
not_hotdog/__init__.py
not_hotdog-0.0.6.dist-info/DESCRIPTION.rst
not_hotdog-0.0.6.dist-info/METADATA
not_hotdog-0.0.6.dist-info/RECORD
not_hotdog-0.0.6.dist-info/WHEEL
not_hotdog-0.0.6.dist-info/metadata.json
not_hotdog-0.0.6.dist-info/top_level.txt
