Metadata-Version: 2.0
Name: not-hotdog
Version: 0.0.6
Summary: Community Tools for classifying not-hotdog type objects
Home-page: UNKNOWN
Author: Covfefe.
Author-email: falcata15@gmail.com
License: BSD
Platform: UNKNOWN
Classifier: Development Status :: 1 - Planning
Classifier: Intended Audience :: End Users/Desktop
Classifier: Intended Audience :: Developers
Classifier: Operating System :: MacOS :: MacOS X
Classifier: Programming Language :: Python :: 2.7
Classifier: Topic :: Software Development
Requires-Dist: numpy (>=1.6.2)
Requires-Dist: protobuf (>=3.1.0)
